shooju/__init__.py
shooju-0.7.8.dist-info/DESCRIPTION.rst
shooju-0.7.8.dist-info/METADATA
shooju-0.7.8.dist-info/RECORD
shooju-0.7.8.dist-info/WHEEL
shooju-0.7.8.dist-info/metadata.json
shooju-0.7.8.dist-info/top_level.txt
