Metadata-Version: 2.0
Name: shooju
Version: 0.7.8
Summary: Official Shooju Client
Home-page: http://shooju.com
Author: Serge Aluker
Author-email: serge@shooju.com
License: MIT
Keywords: data,client,shooju
Platform: UNKNOWN
Requires-Dist: requests (>=2.0.0)
